pyxelator/__init__.py
pyxelator/core.py
pyxelator/utils.py
pyxelator/adapters/__init__.py
pyxelator/adapters/appium.py
pyxelator/adapters/playwright.py
pyxelator/adapters/selenium.py
pyxelator-0.4.0.dist-info/LICENSE
pyxelator-0.4.0.dist-info/METADATA
pyxelator-0.4.0.dist-info/WHEEL
pyxelator-0.4.0.dist-info/top_level.txt
pyxelator-0.4.0.dist-info/RECORD
