Metadata-Version: 2.2
Name: pyxelator
Version: 0.4.0
Summary: Image-based automation for Selenium, Playwright & Appium - locate elements by screenshots
Home-page: https://github.com/idejongkok/pyxelator
Author: Aria Uno Suseno
Author-email: Aria Uno Suseno <uno@idejongkok.com>
Maintainer: Aria Uno Suseno
Project-URL: Homepage, https://github.com/idejongkok/pyxelator
Project-URL: Bug Reports, https://github.com/idejongkok/pyxelator/issues
Project-URL: Source, https://github.com/idejongkok/pyxelator
Project-URL: Instagram, https://instagram.com/idejongkok
Keywords: selenium,playwright,appium,automation,testing,image-recognition,opencv,visual-testing,mobile-automation
Classifier: Development Status :: 4 - Beta
Classifier: Intended Audience :: Developers
Classifier: Topic :: Software Development :: Testing
Classifier: Topic :: Software Development :: Quality Assurance
Classifier: Programming Language :: Python :: 3
Classifier: Programming Language :: Python :: 3.10
Classifier: Programming Language :: Python :: 3.11
Classifier: Programming Language :: Python :: 3.12
Classifier: Programming Language :: Python :: 3.13
Classifier: Operating System :: OS Independent
Requires-Python: >=3.10
License-File: LICENSE
Requires-Dist: opencv-python>=4.5.0
Requires-Dist: numpy>=1.19.0
Provides-Extra: selenium
Requires-Dist: selenium>=4.0.0; extra == "selenium"
Provides-Extra: playwright
Requires-Dist: playwright>=1.20.0; extra == "playwright"
Provides-Extra: appium
Requires-Dist: Appium-Python-Client>=2.0.0; extra == "appium"
Provides-Extra: dev
Requires-Dist: pytest>=7.0.0; extra == "dev"
Requires-Dist: selenium>=4.0.0; extra == "dev"
Requires-Dist: playwright>=1.20.0; extra == "dev"
Requires-Dist: Appium-Python-Client>=2.0.0; extra == "dev"
Dynamic: author
Dynamic: home-page
Dynamic: requires-python
